odoo8_addon_web_dialog_size-8.0.0.1.0.99.dev3-py2.7-nspkg.pth
odoo8_addon_web_dialog_size-8.0.0.1.0.99.dev3.dist-info/DESCRIPTION.rst
odoo8_addon_web_dialog_size-8.0.0.1.0.99.dev3.dist-info/METADATA
odoo8_addon_web_dialog_size-8.0.0.1.0.99.dev3.dist-info/RECORD
odoo8_addon_web_dialog_size-8.0.0.1.0.99.dev3.dist-info/WHEEL
odoo8_addon_web_dialog_size-8.0.0.1.0.99.dev3.dist-info/metadata.json
odoo8_addon_web_dialog_size-8.0.0.1.0.99.dev3.dist-info/namespace_packages.txt
odoo8_addon_web_dialog_size-8.0.0.1.0.99.dev3.dist-info/top_level.txt
odoo_addons/web_dialog_size/README.rst
odoo_addons/web_dialog_size/__init__.py
odoo_addons/web_dialog_size/__openerp__.py
odoo_addons/web_dialog_size/i18n/web_dialog_size.pot
odoo_addons/web_dialog_size/static/description/icon.png
odoo_addons/web_dialog_size/static/src/css/web_dialog_size.css
odoo_addons/web_dialog_size/static/src/js/web_dialog_size.js
odoo_addons/web_dialog_size/static/src/xml/web_dialog_size.xml
odoo_addons/web_dialog_size/view/qweb.xml
