Metadata-Version: 2.0
Name: odoo8-addon-web-dialog-size
Version: 8.0.0.1.0.99.dev3
Summary: A module that lets the user expand a
Home-page: http://acsone.eu
Author: ACSONE SA/NV,Serv. Tecnol. Avanzados - Pedro M. Baeza,Therp BV,Odoo Community Association (OCA)
Author-email: support@odoo-community.org
License: AGPL-3
Platform: UNKNOWN
Classifier: Programming Language :: Python
Classifier: Framework :: Odoo
Classifier: License :: OSI Approved :: GNU Affero General Public License v3
Requires-Python: ~=2.7
Requires-Dist: odoo (<9.0a,>=8.0a)
